setup.py
isBestTool.egg-info/PKG-INFO
isBestTool.egg-info/SOURCES.txt
isBestTool.egg-info/dependency_links.txt
isBestTool.egg-info/not-zip-safe
isBestTool.egg-info/requires.txt
isBestTool.egg-info/top_level.txt
tool/__init__.py
tool/myTool.py