Metadata-Version: 1.0
Name: isBestTool
Version: 1.0
Summary: my Tool
Home-page: UNKNOWN
Author: Du HongYu
Author-email: 837058201@qq.com
License: UNKNOWN
Platform: UNKNOWN
